{
  "columns": 10,
  "image": "mariotilessimple",
  "imageheight": 80,
  "imagewidth": 160,
  "tilecount": 50,
  "tileheight": 16,
  "tilewidth": 16,
  "__comment": "collision: 0 = none, 1 = solid, 2 = breakable, 3 = item",
  "tiles": [
    {
      "id": 0,
      "collision": 1
    },
    {
      "id": 1,
      "collision": 1
    },
    {
      "id": 2,
      "collision": 2
    },
    {
      "id": 3,
      "collision": 0
    },
    {
      "id": 4,
      "collision": 2
    },
    {
      "id": 5,
      "collision": 0
    },
    {
      "id": 6,
      "collision": 0
    },
    {
      "id": 7,
      "collision": 0
    },
    {
      "id": 8,
      "collision": 1
    },
    {
      "id": 9,
      "collision": 3
    },
    {
      "id": 10,
      "collision": 0
    },
    {
      "id": 11,
      "collision": 0
    },
    {
      "id": 12,
      "collision": 0
    },
    {
      "id": 13,
      "collision": 0
    },
    {
      "id": 14,
      "collision": 0
    },
    {
      "id": 15,
      "collision": 0
    },
    {
      "id": 16,
      "collision": 1
    },
    {
      "id": 17,
      "collision": 1
    },
    {
      "id": 18,
      "collision": 1
    },
    {
      "id": 19,
      "collision": 1
    },
    {
      "id": 20,
      "collision": 0
    },
    {
      "id": 21,
      "collision": 0
    },
    {
      "id": 22,
      "collision": 0
    },
    {
      "id": 23,
      "collision": 0
    },
    {
      "id": 24,
      "collision": 0
    },
    {
      "id": 25,
      "collision": 0
    },
    {
      "id": 26,
      "collision": 0
    },
    {
      "id": 27,
      "collision": 0
    },
    {
      "id": 28,
      "collision": 0
    },
    {
      "id": 29,
      "collision": 0
    },
    {
      "id": 30,
      "collision": 0
    },
    {
      "id": 31,
      "collision": 0
    },
    {
      "id": 32,
      "collision": 0
    },
    {
      "id": 33,
      "collision": 0
    },
    {
      "id": 34,
      "collision": 1
    },
    {
      "id": 35,
      "collision": 1
    },
    {
      "id": 36,
      "collision": 1
    },
    {
      "id": 37,
      "collision": 1
    },
    {
      "id": 38,
      "collision": 1
    },
    {
      "id": 39,
      "collision": 1
    },
    {
      "id": 40,
      "collision": 0
    },
    {
      "id": 41,
      "collision": 0
    },
    {
      "id": 42,
      "collision": 0
    },
    {
      "id": 43,
      "collision": 0
    },
    {
      "id": 44,
      "collision": 0
    },
    {
      "id": 45,
      "collision": 0
    },
    {
      "id": 46,
      "collision": 0
    },
    {
      "id": 47,
      "collision": 0
    },
    {
      "id": 48,
      "collision": 0
    },
    {
      "id": 49,
      "collision": 0
    }
  ]
}